zmysql/__init__.py
zmysql/sql.py
zmysql-0.1.1.dist-info/METADATA
zmysql-0.1.1.dist-info/WHEEL
zmysql-0.1.1.dist-info/licenses/LICENSE
zmysql-0.1.1.dist-info/RECORD
