Metadata-Version: 2.1
Name: zmysql
Version: 0.1.1
Summary: zen mysql library
Project-URL: Homepage, https://github.com/inspirare6/zmysql
Project-URL: Bug Tracker, https://github.com/inspirare6/zmysql/issues
Author-email: inspirare6 <inspirare6@163.com>
License-File: LICENSE
Classifier: License :: OSI Approved :: MIT License
Classifier: Operating System :: OS Independent
Classifier: Programming Language :: Python :: 3
Requires-Python: >=3.7
Requires-Dist: pymysql==1.0.2
